[
  { "country": "Afghanistan", "iso3": "AFG", "phone_code": "+93" },
  { "country": "Albania", "iso3": "ALB", "phone_code": "+355" },
  { "country": "Algeria", "iso3": "DZA", "phone_code": "+213" },
  { "country": "American Samoa", "iso3": "ASM", "phone_code": "+1-684" },
  { "country": "Andorra", "iso3": "AND", "phone_code": "+376" },
  { "country": "Angola", "iso3": "AGO", "phone_code": "+244" },
  { "country": "Anguilla", "iso3": "AIA", "phone_code": "+1-264" },
  { "country": "Antarctica", "iso3": "ATA", "phone_code": "+672" },
  { "country": "Antigua and Barbuda", "iso3": "ATG", "phone_code": "+1-268" },
  { "country": "Argentina", "iso3": "ARG", "phone_code": "+54" },
  { "country": "Armenia", "iso3": "ARM", "phone_code": "+374" },
  { "country": "Aruba", "iso3": "ABW", "phone_code": "+297" },
  { "country": "Australia", "iso3": "AUS", "phone_code": "+61" },
  { "country": "Austria", "iso3": "AUT", "phone_code": "+43" },
  { "country": "Azerbaijan", "iso3": "AZE", "phone_code": "+994" },
  { "country": "Bahamas", "iso3": "BHS", "phone_code": "+1-242" },
  { "country": "Bahrain", "iso3": "BHR", "phone_code": "+973" },
  { "country": "Bangladesh", "iso3": "BGD", "phone_code": "+880" },
  { "country": "Barbados", "iso3": "BRB", "phone_code": "+1-246" },
  { "country": "Belarus", "iso3": "BLR", "phone_code": "+375" },
  { "country": "Belgium", "iso3": "BEL", "phone_code": "+32" },
  { "country": "Belize", "iso3": "BLZ", "phone_code": "+501" },
  { "country": "Benin", "iso3": "BEN", "phone_code": "+229" },
  { "country": "Bermuda", "iso3": "BMU", "phone_code": "+1-441" },
  { "country": "Bhutan", "iso3": "BTN", "phone_code": "+975" },
  { "country": "Bolivia", "iso3": "BOL", "phone_code": "+591" },
  { "country": "Bosnia and Herzegovina", "iso3": "BIH", "phone_code": "+387" },
  { "country": "Botswana", "iso3": "BWA", "phone_code": "+267" },
  { "country": "Brazil", "iso3": "BRA", "phone_code": "+55" },
  { "country": "British Indian Ocean Territory", "iso3": "IOT", "phone_code": "+246" },
  { "country": "Brunei", "iso3": "BRN", "phone_code": "+673" },
  { "country": "Bulgaria", "iso3": "BGR", "phone_code": "+359" },
  { "country": "Burkina Faso", "iso3": "BFA", "phone_code": "+226" },
  { "country": "Burundi", "iso3": "BDI", "phone_code": "+257" },
  { "country": "Cabo Verde", "iso3": "CPV", "phone_code": "+238" },
  { "country": "Cambodia", "iso3": "KHM", "phone_code": "+855" },
  { "country": "Cameroon", "iso3": "CMR", "phone_code": "+237" },
  { "country": "Canada", "iso3": "CAN", "phone_code": "+1" },
  { "country": "Cayman Islands", "iso3": "CYM", "phone_code": "+1-345" },
  { "country": "Central African Republic", "iso3": "CAF", "phone_code": "+236" },
  { "country": "Chad", "iso3": "TCD", "phone_code": "+235" },
  { "country": "Chile", "iso3": "CHL", "phone_code": "+56" },
  { "country": "China", "iso3": "CHN", "phone_code": "+86" },
  { "country": "Colombia", "iso3": "COL", "phone_code": "+57" },
  { "country": "Comoros", "iso3": "COM", "phone_code": "+269" },
  { "country": "Congo (Congo-Brazzaville)", "iso3": "COG", "phone_code": "+242" },
  { "country": "Congo (Democratic Republic)", "iso3": "COD", "phone_code": "+243" },
  { "country": "Cook Islands", "iso3": "COK", "phone_code": "+682" },
  { "country": "Costa Rica", "iso3": "CRI", "phone_code": "+506" },
  { "country": "Croatia", "iso3": "HRV", "phone_code": "+385" },
  { "country": "Cuba", "iso3": "CUB", "phone_code": "+53" },
  { "country": "Cyprus", "iso3": "CYP", "phone_code": "+357" },
  { "country": "Czech Republic", "iso3": "CZE", "phone_code": "+420" },
  { "country": "Denmark", "iso3": "DNK", "phone_code": "+45" },
  { "country": "Djibouti", "iso3": "DJI", "phone_code": "+253" },
  { "country": "Dominica", "iso3": "DMA", "phone_code": "+1-767" },
  { "country": "Dominican Republic", "iso3": "DOM", "phone_code": "+1-809" },
  { "country": "Ecuador", "iso3": "ECU", "phone_code": "+593" },
  { "country": "Egypt", "iso3": "EGY", "phone_code": "+20" },
  { "country": "El Salvador", "iso3": "SLV", "phone_code": "+503" },
  { "country": "Equatorial Guinea", "iso3": "GNQ", "phone_code": "+240" },
  { "country": "Eritrea", "iso3": "ERI", "phone_code": "+291" },
  { "country": "Estonia", "iso3": "EST", "phone_code": "+372" },
  { "country": "Eswatini", "iso3": "SWZ", "phone_code": "+268" },
  { "country": "Ethiopia", "iso3": "ETH", "phone_code": "+251" },
  { "country": "Fiji", "iso3": "FJI", "phone_code": "+679" },
  { "country": "Finland", "iso3": "FIN", "phone_code": "+358" },
  { "country": "France", "iso3": "FRA", "phone_code": "+33" },
  { "country": "Gabon", "iso3": "GAB", "phone_code": "+241" },
  { "country": "Gambia", "iso3": "GMB", "phone_code": "+220" },
  { "country": "Georgia", "iso3": "GEO", "phone_code": "+995" },
  { "country": "Germany", "iso3": "DEU", "phone_code": "+49" },
  { "country": "Ghana", "iso3": "GHA", "phone_code": "+233" },
  { "country": "Greece", "iso3": "GRC", "phone_code": "+30" },
  { "country": "Grenada", "iso3": "GRD", "phone_code": "+1-473" },
  { "country": "Guatemala", "iso3": "GTM", "phone_code": "+502" },
  { "country": "Guinea", "iso3": "GIN", "phone_code": "+224" },
  { "country": "Guinea-Bissau", "iso3": "GNB", "phone_code": "+245" },
  { "country": "Guyana", "iso3": "GUY", "phone_code": "+592" },
  { "country": "Haiti", "iso3": "HTI", "phone_code": "+509" },
  { "country": "Honduras", "iso3": "HND", "phone_code": "+504" },
  { "country": "Hungary", "iso3": "HUN", "phone_code": "+36" },
  { "country": "Iceland", "iso3": "ISL", "phone_code": "+354" },
  { "country": "India", "iso3": "IND", "phone_code": "+91" },
  { "country": "Indonesia", "iso3": "IDN", "phone_code": "+62" },
  { "country": "Iran", "iso3": "IRN", "phone_code": "+98" },
  { "country": "Iraq", "iso3": "IRQ", "phone_code": "+964" },
  { "country": "Ireland", "iso3": "IRL", "phone_code": "+353" },
  { "country": "Israel", "iso3": "ISR", "phone_code": "+972" },
  { "country": "Italy", "iso3": "ITA", "phone_code": "+39" },
  { "country": "Jamaica", "iso3": "JAM", "phone_code": "+1-876" },
  { "country": "Japan", "iso3": "JPN", "phone_code": "+81" },
  { "country": "Jordan", "iso3": "JOR", "phone_code": "+962" },
  { "country": "Kazakhstan", "iso3": "KAZ", "phone_code": "+7" },
  { "country": "Kenya", "iso3": "KEN", "phone_code": "+254" },
  { "country": "Kiribati", "iso3": "KIR", "phone_code": "+686" },
  { "country": "Kuwait", "iso3": "KWT", "phone_code": "+965" },
  { "country": "Kyrgyzstan", "iso3": "KGZ", "phone_code": "+996" },
  { "country": "Laos", "iso3": "LAO", "phone_code": "+856" },
  { "country": "Latvia", "iso3": "LVA", "phone_code": "+371" },
  { "country": "Lebanon", "iso3": "LBN", "phone_code": "+961" },
  { "country": "Lesotho", "iso3": "LSO", "phone_code": "+266" },
  { "country": "Liberia", "iso3": "LBR", "phone_code": "+231" },
  { "country": "Libya", "iso3": "LBY", "phone_code": "+218" },
  { "country": "Liechtenstein", "iso3": "LIE", "phone_code": "+423" },
  { "country": "Lithuania", "iso3": "LTU", "phone_code": "+370" },
  { "country": "Luxembourg", "iso3": "LUX", "phone_code": "+352" },
  { "country": "Madagascar", "iso3": "MDG", "phone_code": "+261" },
  { "country": "Malawi", "iso3": "MWI", "phone_code": "+265" },
  { "country": "Malaysia", "iso3": "MYS", "phone_code": "+60" },
  { "country": "Maldives", "iso3": "MDV", "phone_code": "+960" },
  { "country": "Mali", "iso3": "MLI", "phone_code": "+223" },
  { "country": "Malta", "iso3": "MLT", "phone_code": "+356" },
  { "country": "Marshall Islands", "iso3": "MHL", "phone_code": "+692" },
  { "country": "Mauritania", "iso3": "MRT", "phone_code": "+222" },
  { "country": "Mauritius", "iso3": "MUS", "phone_code": "+230" },
  { "country": "Mexico", "iso3": "MEX", "phone_code": "+52" },
  { "country": "Micronesia", "iso3": "FSM", "phone_code": "+691" },
  { "country": "Moldova", "iso3": "MDA", "phone_code": "+373" },
  { "country": "Monaco", "iso3": "MCO", "phone_code": "+377" },
  { "country": "Mongolia", "iso3": "MNG", "phone_code": "+976" },
  { "country": "Montenegro", "iso3": "MNE", "phone_code": "+382" },
  { "country": "Morocco", "iso3": "MAR", "phone_code": "+212" },
  { "country": "Mozambique", "iso3": "MOZ", "phone_code": "+258" },
  { "country": "Myanmar", "iso3": "MMR", "phone_code": "+95" },
  { "country": "Namibia", "iso3": "NAM", "phone_code": "+264" },
  { "country": "Nauru", "iso3": "NRU", "phone_code": "+674" },
  { "country": "Nepal", "iso3": "NPL", "phone_code": "+977" },
  { "country": "Netherlands", "iso3": "NLD", "phone_code": "+31" },
  { "country": "New Zealand", "iso3": "NZL", "phone_code": "+64" },
  { "country": "Nicaragua", "iso3": "NIC", "phone_code": "+505" },
  { "country": "Niger", "iso3": "NER", "phone_code": "+227" },
  { "country": "Nigeria", "iso3": "NGA", "phone_code": "+234" },
  { "country": "North Macedonia", "iso3": "MKD", "phone_code": "+389" },
  { "country": "Norway", "iso3": "NOR", "phone_code": "+47" },
  { "country": "Oman", "iso3": "OMN", "phone_code": "+968" },
  { "country": "Pakistan", "iso3": "PAK", "phone_code": "+92" },
  { "country": "Palau", "iso3": "PLW", "phone_code": "+680" },
  { "country": "Panama", "iso3": "PAN", "phone_code": "+507" },
  { "country": "Papua New Guinea", "iso3": "PNG", "phone_code": "+675" },
  { "country": "Paraguay", "iso3": "PRY", "phone_code": "+595" },
  { "country": "Peru", "iso3": "PER", "phone_code": "+51" },
  { "country": "Philippines", "iso3": "PHL", "phone_code": "+63" },
  { "country": "Poland", "iso3": "POL", "phone_code": "+48" },
  { "country": "Portugal", "iso3": "PRT", "phone_code": "+351" },
  { "country": "Qatar", "iso3": "QAT", "phone_code": "+974" },
  { "country": "Romania", "iso3": "ROU", "phone_code": "+40" },
  { "country": "Russia", "iso3": "RUS", "phone_code": "+7" },
  { "country": "Rwanda", "iso3": "RWA", "phone_code": "+250" },
  { "country": "Saint Kitts and Nevis", "iso3": "KNA", "phone_code": "+1-869" },
  { "country": "Saint Lucia", "iso3": "LCA", "phone_code": "+1-758" },
  { "country": "Saint Vincent and the Grenadines", "iso3": "VCT", "phone_code": "+1-784" },
  { "country": "Samoa", "iso3": "WSM", "phone_code": "+685" },
  { "country": "San Marino", "iso3": "SMR", "phone_code": "+378" },
  { "country": "Sao Tome and Principe", "iso3": "STP", "phone_code": "+239" },
  { "country": "Saudi Arabia", "iso3": "SAU", "phone_code": "+966" },
  { "country": "Senegal", "iso3": "SEN", "phone_code": "+221" },
  { "country": "Serbia", "iso3": "SRB", "phone_code": "+381" },
  { "country": "Seychelles", "iso3": "SYC", "phone_code": "+248" },
  { "country": "Sierra Leone", "iso3": "SLE", "phone_code": "+232" },
  { "country": "Singapore", "iso3": "SGP", "phone_code": "+65" },
  { "country": "Slovakia", "iso3": "SVK", "phone_code": "+421" },
  { "country": "Slovenia", "iso3": "SVN", "phone_code": "+386" },
  { "country": "Solomon Islands", "iso3": "SLB", "phone_code": "+677" },
  { "country": "Somalia", "iso3": "SOM", "phone_code": "+252" },
  { "country": "South Africa", "iso3": "ZAF", "phone_code": "+27" },
  { "country": "South Korea", "iso3": "KOR", "phone_code": "+82" },
  { "country": "South Sudan", "iso3": "SSD", "phone_code": "+211" },
  { "country": "Spain", "iso3": "ESP", "phone_code": "+34" },
  { "country": "Sri Lanka", "iso3": "LKA", "phone_code": "+94" },
  { "country": "Sudan", "iso3": "SDN", "phone_code": "+249" },
  { "country": "Suriname", "iso3": "SUR", "phone_code": "+597" },
  { "country": "Sweden", "iso3": "SWE", "phone_code": "+46" },
  { "country": "Switzerland", "iso3": "CHE", "phone_code": "+41" },
  { "country": "Syria", "iso3": "SYR", "phone_code": "+963" },
  { "country": "Taiwan", "iso3": "TWN", "phone_code": "+886" },
  { "country": "Tajikistan", "iso3": "TJK", "phone_code": "+992" },
  { "country": "Tanzania", "iso3": "TZA", "phone_code": "+255" },
  { "country": "Thailand", "iso3": "THA", "phone_code": "+66" },
  { "country": "Timor-Leste", "iso3": "TLS", "phone_code": "+670" },
  { "country": "Togo", "iso3": "TGO", "phone_code": "+228" },
  { "country": "Tonga", "iso3": "TON", "phone_code": "+676" },
  { "country": "Trinidad and Tobago", "iso3": "TTO", "phone_code": "+1-868" },
  { "country": "Tunisia", "iso3": "TUN", "phone_code": "+216" },
  { "country": "Turkey", "iso3": "TUR", "phone_code": "+90" },
  { "country": "Turkmenistan", "iso3": "TKM", "phone_code": "+993" },
  { "country": "Tuvalu", "iso3": "TUV", "phone_code": "+688" },
  { "country": "Uganda", "iso3": "UGA", "phone_code": "+256" },
  { "country": "Ukraine", "iso3": "UKR", "phone_code": "+380" },
  { "country": "United Arab Emirates", "iso3": "ARE", "phone_code": "+971" },
  { "country": "United Kingdom", "iso3": "GBR", "phone_code": "+44" },
  { "country": "United States", "iso3": "USA", "phone_code": "+1" },
  { "country": "Uruguay", "iso3": "URY", "phone_code": "+598" },
  { "country": "Uzbekistan", "iso3": "UZB", "phone_code": "+998" },
  { "country": "Vanuatu", "iso3": "VUT", "phone_code": "+678" },
  { "country": "Vatican City", "iso3": "VAT", "phone_code": "+379" },
  { "country": "Venezuela", "iso3": "VEN", "phone_code": "+58" },
  { "country": "Vietnam", "iso3": "VNM", "phone_code": "+84" },
  { "country": "Yemen", "iso3": "YEM", "phone_code": "+967" },
  { "country": "Zambia", "iso3": "ZMB", "phone_code": "+260" },
  { "country": "Zimbabwe", "iso3": "ZWE", "phone_code": "+263" }
]
